django_fabric/__init__.py
django_fabric/base.py
django_fabric/commands.py
django_fabric/mixins.py
django_fabric/notifications.py
django_fabric/test_helpers.py
django_fabric/uwsgi.py
django_fabric-2.1.0.dist-info/DESCRIPTION.rst
django_fabric-2.1.0.dist-info/entry_points.txt
django_fabric-2.1.0.dist-info/METADATA
django_fabric-2.1.0.dist-info/metadata.json
django_fabric-2.1.0.dist-info/RECORD
django_fabric-2.1.0.dist-info/top_level.txt
django_fabric-2.1.0.dist-info/WHEEL
tests/__init__.py
tests/django_settings.py
tests/helpers.py
tests/run.py
tests/test_base.py
