Metadata-Version: 2.0
Name: django-fabric
Version: 2.1.0
Summary: a generic fabric utility class for django projects
Home-page: https://github.com/mocco/django-fabric
Author: Rolf Erik Lekang
Author-email: rolf@mocco.no
License: UNKNOWN
Platform: UNKNOWN
Classifier: Programming Language :: Python
Classifier: Topic :: Software Development :: Libraries :: Python Modules
Classifier: Environment :: Web Environment
Classifier: Operating System :: OS Independent
Classifier: Natural Language :: English
Requires-Dist: fabric
Requires-Dist: django
Requires-Dist: requests
